{
  "term": "mapahofiay",
  "properties": {
    "id": "",
    "tags": [],
    "level": {
      "cefr": "",
      "ilrdf": ""
    },
    "basic": {
      "language": "Amis (Pangcah)",
      "language_code": "ami",
      "dialect": "uncertain",
      "origin": "Amis Moedict",
      "author_dictionary": "Safulo Kacaw Lalanges Hakasi",
      "author_datasystem": "Mirusa Usiliq",
      "date": "2023/08/04",
      "time": "00:00",
      "location": "Hualien, Taiwan",
      "device": "MacOS",
      "license": "MIT",
      "reference": "..."
    }
  },
  "linguistics": {
    "pos": "",
    "ipa": "mapahofʔiʔaj"
  },
  "nyms": {
    "synonyms": [],
    "antonyms": [],
    "hyponyms": [],
    "metonyms": [],
    "homonyms": [],
    "heternyms": [],
    "homographs": [],
    "polysemous": [],
    "synecdoche": [],
    "word_family": []
  },
  "definitions": [
    {
      "language": "zh-tw",
      "explaination": "被獎賞了，被獎勵了，得到獎賞了。",
      "example": "",
      "synonyms": "",
      "usage": "",
      "tips": ""
    },
    {
      "language": "zh-tw",
      "explaination": "指被獎賞或獎勵的（對象）。",
      "example": "￹`Mapahofiay~ `no~ `tapang~ `cingra~.￺￻他得到了首長的獎勵了。",
      "synonyms": "",
      "usage": "",
      "tips": ""
    }
  ],
  "declensions": [],
  "conjugation": []
}