{
  "term": "matenakay",
  "properties": {
    "id": "",
    "tags": [],
    "level": {
      "cefr": "",
      "ilrdf": ""
    },
    "basic": {
      "language": "Amis (Pangcah)",
      "language_code": "ami",
      "dialect": "uncertain",
      "author_dictionary": "Safulo Kacaw Lalanges Hakasi",
      "author_datasystem": "Mirusa Usiliq",
      "date": "2023/08/04",
      "time": "00:00",
      "location": "Hualien, Taiwan",
      "device": "MacOS",
      "license": "MIT",
      "reference": "...",
      "pos": "stem"
    }
  },
  "linguistics": {
    "pos": "",
    "ipa": "matənakaj"
  },
  "nyms": {
    "synonyms": [],
    "antonyms": [],
    "hyponyms": [],
    "metonyms": [],
    "homonyms": [],
    "heternyms": [],
    "homographs": [],
    "polysemous": [],
    "synecdoche": [],
    "word_family": []
  },
  "definitions": [
    {
      "language": "zh-tw",
      "explaination": "散布出去了，傳播出去了。",
      "example": "",
      "synonyms": "",
      "usage": "",
      "tips": ""
    },
    {
      "language": "zh-tw",
      "explaination": "指散布、傳播的（對象）。",
      "example": "￹`Matenakay~ `a~ `sowal~ `no~ `Kawas~.￺￻所傳播的上帝福音。",
      "synonyms": "",
      "usage": "",
      "tips": ""
    }
  ],
  "declensions": [],
  "conjugation": []
}