{
  "term": "mi'osian",
  "properties": {
    "id": "",
    "tags": [],
    "level": {
      "cefr": "",
      "ilrdf": ""
    },
    "basic": {
      "language": "Amis (Pangcah)",
      "language_code": "ami",
      "dialect": "uncertain",
      "author_dictionary": "Safulo Kacaw Lalanges Hakasi",
      "author_datasystem": "Mirusa Usiliq",
      "date": "2023/08/04",
      "time": "00:00",
      "location": "Hualien, Taiwan",
      "device": "MacOS",
      "license": "MIT",
      "reference": "...",
      "pos": "stem"
    }
  },
  "linguistics": {
    "pos": "",
    "ipa": "miʡosʔiʔan"
  },
  "nyms": {
    "synonyms": [],
    "antonyms": [],
    "hyponyms": [],
    "metonyms": [],
    "homonyms": [],
    "heternyms": [],
    "homographs": [],
    "polysemous": [],
    "synecdoche": [],
    "word_family": []
  },
  "definitions": [
    {
      "language": "zh-tw",
      "explaination": "把…計算了、數好了。",
      "example": "￹`Mi'osian~ `ako~ `ko~ `mi'adopan~ `iso~, `tosaay~ `ko~ `fafoy~, `toloay~ `ko~ `takolil~.￺￻我把你獵獲的動物都計算了，有兩隻野豬，三隻兔子。",
      "synonyms": "",
      "usage": "",
      "tips": ""
    },
    {
      "language": "zh-tw",
      "explaination": "指所計算的（物件、東西）。",
      "example": "￹`O~ `pawti~ `sa~ `ko~ `mi'osian~ `niyam~ `a~ `panay~ `itiya~ `ho~.￺￻我們過去計算稻穀以一麻袋為單位。",
      "synonyms": "",
      "usage": "",
      "tips": ""
    }
  ],
  "declensions": [],
  "conjugation": []
}