{
  "term": "mici'iwi'iwian",
  "properties": {
    "id": "",
    "tags": [],
    "level": {
      "cefr": "",
      "ilrdf": ""
    },
    "basic": {
      "language": "Amis (Pangcah)",
      "language_code": "ami",
      "dialect": "uncertain",
      "origin": "Amis Moedict",
      "author_dictionary": "Safulo Kacaw Lalanges Hakasi",
      "author_datasystem": "Mirusa Usiliq",
      "date": "2023/08/04",
      "time": "00:00",
      "location": "Hualien, Taiwan",
      "device": "MacOS",
      "license": "MIT",
      "reference": "..."
    }
  },
  "linguistics": {
    "pos": "",
    "ipa": "mit͡siʡiwiʡiwʔiʔan"
  },
  "nyms": {
    "synonyms": [],
    "antonyms": [],
    "hyponyms": [],
    "metonyms": [],
    "homonyms": [],
    "heternyms": [],
    "homographs": [],
    "polysemous": [],
    "synecdoche": [],
    "word_family": []
  },
  "definitions": [
    {
      "language": "zh-tw",
      "explaination": "把…造成各種分歧了、分流了。",
      "example": "￹`Mici'iwi'iwian~ `kora~ `kiwkay~.￺￻那些教會已分歧林立了。",
      "synonyms": "",
      "usage": "",
      "tips": ""
    },
    {
      "language": "zh-tw",
      "explaination": "指造成許多分歧、分流的（物件、地方）。",
      "example": "￹`Mici'iwi'iwian~ `a~ `kapot~.￺￻派系複雜的團體。",
      "synonyms": "`miciriciridan~",
      "usage": "",
      "tips": ""
    }
  ],
  "declensions": [],
  "conjugation": []
}