{
  "term": "mihintaay",
  "properties": {
    "id": "",
    "tags": [],
    "level": {
      "cefr": "",
      "ilrdf": ""
    },
    "basic": {
      "language": "Amis (Pangcah)",
      "language_code": "ami",
      "dialect": "uncertain",
      "origin": "Amis Moedict",
      "author_dictionary": "Safulo Kacaw Lalanges Hakasi",
      "author_datasystem": "Mirusa Usiliq",
      "date": "2023/08/04",
      "time": "00:00",
      "location": "Hualien, Taiwan",
      "device": "MacOS",
      "license": "MIT",
      "reference": "..."
    }
  },
  "linguistics": {
    "pos": "",
    "ipa": "mihintʔaʔaj"
  },
  "nyms": {
    "synonyms": [],
    "antonyms": [],
    "hyponyms": [],
    "metonyms": [],
    "homonyms": [],
    "heternyms": [],
    "homographs": [],
    "polysemous": [],
    "synecdoche": [],
    "word_family": []
  },
  "definitions": [
    {
      "language": "zh-tw",
      "explaination": "在邀請、邀約了、約請了。",
      "example": "￹`Mihintaay~ `ci~ `Panay~ `takowanan~.￺￻`Panay~（巴奈）在邀請我了。",
      "synonyms": "",
      "usage": "",
      "tips": ""
    },
    {
      "language": "zh-tw",
      "explaination": "指邀請者，約請者。",
      "example": "￹`O~ `kakeridan~ `no~ `cefang~ `ko~ `mihintaay~ `to~ `singsi~.￺￻邀請老師的班代。",
      "synonyms": "",
      "usage": "",
      "tips": ""
    }
  ],
  "declensions": [],
  "conjugation": []
}