{
  "term": "mirepelay",
  "properties": {
    "id": "",
    "tags": [],
    "level": {
      "cefr": "",
      "ilrdf": ""
    },
    "basic": {
      "language": "Amis (Pangcah)",
      "language_code": "ami",
      "dialect": "uncertain",
      "author_dictionary": "Safulo Kacaw Lalanges Hakasi",
      "author_datasystem": "Mirusa Usiliq",
      "date": "2023/08/04",
      "time": "00:00",
      "location": "Hualien, Taiwan",
      "device": "MacOS",
      "license": "MIT",
      "reference": "...",
      "pos": "stem"
    }
  },
  "linguistics": {
    "pos": "",
    "ipa": "miɾəpəlaj"
  },
  "nyms": {
    "synonyms": [],
    "antonyms": [],
    "hyponyms": [],
    "metonyms": [],
    "homonyms": [],
    "heternyms": [],
    "homographs": [],
    "polysemous": [],
    "synecdoche": [],
    "word_family": []
  },
  "definitions": [
    {
      "language": "zh-tw",
      "explaination": "正在追捕、捕獲、捉住了。",
      "example": "￹`Mirepelay~ ci`nira~ `to~ `mitakaway~ `a~ `tamdaw~.￺￻他在抓小偷。",
      "synonyms": "`mirepetay~",
      "usage": "",
      "tips": ""
    },
    {
      "language": "zh-tw",
      "explaination": "指追捕者，捕獲者，捕捉者。",
      "example": "￹`Mirepelay~ `a~ `kincac~.￺￻逮人的員警。",
      "synonyms": "",
      "usage": "",
      "tips": ""
    }
  ],
  "declensions": [],
  "conjugation": []
}