{
  "term": "misakapahay",
  "properties": {
    "id": "",
    "tags": [],
    "level": {
      "cefr": "",
      "ilrdf": ""
    },
    "basic": {
      "language": "Amis (Pangcah)",
      "language_code": "ami",
      "dialect": "uncertain",
      "author_dictionary": "Safulo Kacaw Lalanges Hakasi",
      "author_datasystem": "Mirusa Usiliq",
      "date": "2023/08/04",
      "time": "00:00",
      "location": "Hualien, Taiwan",
      "device": "MacOS",
      "license": "MIT",
      "reference": "...",
      "pos": "stem"
    }
  },
  "linguistics": {
    "pos": "",
    "ipa": "misakapahaj"
  },
  "nyms": {
    "synonyms": [],
    "antonyms": [],
    "hyponyms": [],
    "metonyms": [],
    "homonyms": [],
    "heternyms": [],
    "homographs": [],
    "polysemous": [],
    "synecdoche": [],
    "word_family": []
  },
  "definitions": [
    {
      "language": "zh-tw",
      "explaination": "正在美化、裝飾著，弄漂亮了。",
      "example": "￹`Misakapahay~ `kako~ `to~ `wawa~ `ako~.￺￻我正在打扮我的孩子。",
      "synonyms": "",
      "usage": "",
      "tips": ""
    },
    {
      "language": "zh-tw",
      "explaination": "指美化者，裝飾者，把東西弄漂亮的人。",
      "example": "￹`Misakapahay~ `a~ `sayxo~.￺￻美化師，裝飾師。",
      "synonyms": "",
      "usage": "",
      "tips": ""
    }
  ],
  "declensions": [],
  "conjugation": []
}