{
  "term": "sapipakahemek",
  "properties": {
    "id": "",
    "tags": [],
    "level": {
      "cefr": "",
      "ilrdf": ""
    },
    "basic": {
      "language": "Amis (Pangcah)",
      "language_code": "ami",
      "dialect": "uncertain",
      "author_dictionary": "Safulo Kacaw Lalanges Hakasi",
      "author_datasystem": "Mirusa Usiliq",
      "date": "2023/08/04",
      "time": "00:00",
      "location": "Hualien, Taiwan",
      "device": "MacOS",
      "license": "MIT",
      "reference": "...",
      "pos": "stem"
    }
  },
  "linguistics": {
    "pos": "",
    "ipa": "sapipakahəmək"
  },
  "nyms": {
    "synonyms": [],
    "antonyms": [],
    "hyponyms": [],
    "metonyms": [],
    "homonyms": [],
    "heternyms": [],
    "homographs": [],
    "polysemous": [],
    "synecdoche": [],
    "word_family": []
  },
  "definitions": [
    {
      "language": "zh-tw",
      "explaination": "讓人高興、愉快使用的器具、逗樂的用器。",
      "example": "￹`Sapipakahemek~ `to~ `tao~ `a~ `sowal~.￺￻讓別人高興的話，相聲。",
      "synonyms": "",
      "usage": "",
      "tips": ""
    }
  ],
  "declensions": [],
  "conjugation": []
}