{
  "term": "so^elinay",
  "properties": {
    "id": "",
    "tags": [],
    "level": {
      "cefr": "",
      "ilrdf": ""
    },
    "basic": {
      "language": "Amis (Pangcah)",
      "language_code": "ami",
      "dialect": "uncertain",
      "origin": "Amis Moedict",
      "author_dictionary": "Safulo Kacaw Lalanges Hakasi",
      "author_datasystem": "Mirusa Usiliq",
      "date": "2023/08/04",
      "time": "00:00",
      "location": "Hualien, Taiwan",
      "device": "MacOS",
      "license": "MIT",
      "reference": "..."
    }
  },
  "linguistics": {
    "pos": "",
    "ipa": "soʔəlinaj"
  },
  "nyms": {
    "synonyms": [],
    "antonyms": [],
    "hyponyms": [],
    "metonyms": [],
    "homonyms": [],
    "heternyms": [],
    "homographs": [],
    "polysemous": [],
    "synecdoche": [],
    "word_family": []
  },
  "definitions": [
    {
      "language": "zh-tw",
      "explaination": "真實了、可信了、真的了。",
      "example": "￹`So^elinay~ `cingra~ `a~ `mafana'~.￺￻他真懂了。",
      "synonyms": "",
      "usage": "",
      "tips": ""
    },
    {
      "language": "zh-tw",
      "explaination": "真實的、可信的。",
      "example": "￹`So^elinay~ `a~ `demak~.￺￻真實的事情。",
      "synonyms": "",
      "usage": "",
      "tips": ""
    }
  ],
  "declensions": [],
  "conjugation": []
}