{
  "term": "'angcep",
  "properties": {
    "id": "",
    "tags": [],
    "level": {
      "cefr": "",
      "ilrdf": ""
    },
    "basic": {
      "language": "Amis (Pangcah)",
      "language_code": "ami",
      "dialect": "uncertain",
      "author_dictionary": "Safulo Kacaw Lalanges Hakasi",
      "author_datasystem": "Mirusa Usiliq",
      "date": "2023/08/04",
      "time": "00:00",
      "location": "Hualien, Taiwan",
      "device": "MacOS",
      "license": "MIT",
      "reference": "..."
    }
  },
  "linguistics": {
    "pos": "",
    "ipa": "ʡaŋt͡səp"
  },
  "nyms": {
    "synonyms": [],
    "antonyms": [],
    "hyponyms": [],
    "metonyms": [],
    "homonyms": [],
    "heternyms": [],
    "homographs": [],
    "polysemous": [],
    "synecdoche": [],
    "word_family": []
  },
  "definitions": [
    {
      "language": "zh-tw",
      "explaination": "飯焦味，燒焦。",
      "example": "￹`'Angcep~ `ko~ `holo~ `ni~ `mamo~.￺￻阿嬤煮的飯有燒焦味。",
      "synonyms": "",
      "usage": "",
      "tips": ""
    },
    {
      "language": "zh-tw",
      "explaination": "發臭。",
      "example": "",
      "synonyms": "aucoh",
      "usage": "",
      "tips": ""
    },
    {
      "language": "zh-tw",
      "explaination": "飯燒焦味，糊焦味。",
      "example": "",
      "synonyms": "",
      "usage": "",
      "tips": ""
    },
    {
      "language": "zh-tw",
      "explaination": "飯焦味。",
      "example": "",
      "synonyms": "`'ancep~",
      "usage": "",
      "tips": ""
    },
    {
      "language": "zh-tw",
      "explaination": "飯糊味，糊焦味。",
      "example": "",
      "synonyms": "",
      "usage": "",
      "tips": ""
    }
  ],
  "declensions": [],
  "conjugation": []
}