{
  "term": "nakaharekan",
  "properties": {
    "id": "",
    "tags": [],
    "level": {
      "cefr": "",
      "ilrdf": ""
    },
    "basic": {
      "language": "Amis (Pangcah)",
      "language_code": "ami",
      "dialect": "uncertain",
      "author_dictionary": "Safulo Kacaw Lalanges Hakasi",
      "author_datasystem": "Mirusa Usiliq",
      "date": "2023/08/04",
      "time": "00:00",
      "location": "Hualien, Taiwan",
      "device": "MacOS",
      "license": "MIT",
      "reference": "...",
      "pos": "stem"
    }
  },
  "linguistics": {
    "pos": "",
    "ipa": "nakahaɾəkan"
  },
  "nyms": {
    "synonyms": [],
    "antonyms": [],
    "hyponyms": [],
    "metonyms": [],
    "homonyms": [],
    "heternyms": [],
    "homographs": [],
    "polysemous": [],
    "synecdoche": [],
    "word_family": []
  },
  "definitions": [
    {
      "language": "zh-tw",
      "explaination": "自從工作或事情結束以後。",
      "example": "￹）Naka`harek~an `a~ `matayal~ `pahanhan~ `cingra~.￺￻自從工作結束之後他就休息了一下。",
      "synonyms": "",
      "usage": "",
      "tips": ""
    },
    {
      "language": "zh-tw",
      "explaination": "（同`herek~。",
      "example": "",
      "synonyms": "",
      "usage": "",
      "tips": ""
    }
  ],
  "declensions": [],
  "conjugation": []
}